accesser/__init__.py
accesser/__main__.py
accesser/config.toml
accesser/pac
accesser/rules.toml
accesser/utils/__init__.py
accesser/utils/cert_verify.py
accesser/utils/certmanager.py
accesser/utils/importca.py
accesser/utils/log.py
accesser/utils/setting.py
accesser/utils/sysproxy.py
accesser-0.11.1.dist-info/licenses/LICENSE
accesser-0.11.1.dist-info/METADATA
accesser-0.11.1.dist-info/WHEEL
accesser-0.11.1.dist-info/entry_points.txt
accesser-0.11.1.dist-info/top_level.txt
accesser-0.11.1.dist-info/RECORD
