Metadata-Version: 2.4
Name: accesser
Version: 0.11.1
Summary: 🌏一个解决SNI RST导致维基百科、Pixiv等站点无法访问的工具 | A tool for solving SNI RST
Author: URenko
Project-URL: Homepage, https://github.com/URenko/Accesser
Project-URL: Bug Tracker, https://github.com/URenko/Accesser/issues
Classifier: Programming Language :: Python :: 3
Classifier: License :: OSI Approved :: GNU General Public License v3 (GPLv3)
Classifier: Operating System :: OS Independent
Requires-Python: >=3.10
License-File: LICENSE
Requires-Dist: packaging
Requires-Dist: cryptography
Requires-Dist: tld
Requires-Dist: dnspython>=2.7
Requires-Dist: tomli>=1.1.0; python_version < "3.11"
Provides-Extra: doh
Requires-Dist: dnspython[doh]; extra == "doh"
Provides-Extra: doq
Requires-Dist: dnspython[doq]; extra == "doq"
Dynamic: license-file
